snakeoil/__init__.py
snakeoil/admin.py
snakeoil/apps.py
snakeoil/jinja2.py
snakeoil/models.py
snakeoil/py.typed
snakeoil/types.py
snakeoil/utils.py
snakeoil/jinja2/snakeoil/seo.jinja2
snakeoil/migrations/0001_initial.py
snakeoil/migrations/0002_auto_20200727_0951.py
snakeoil/migrations/__init__.py
snakeoil/templates/snakeoil/seo.html
snakeoil/templatetags/__init__.py
snakeoil/templatetags/snakeoil.py
django_snakeoil-2.0.dist-info/LICENSE
django_snakeoil-2.0.dist-info/METADATA
django_snakeoil-2.0.dist-info/WHEEL
django_snakeoil-2.0.dist-info/top_level.txt
django_snakeoil-2.0.dist-info/RECORD
