Metadata-Version: 2.1
Name: django-snakeoil
Version: 2.0
Summary: Simple SEO & meta tag management for Django
Author-email: Tom Carrick <tom@carrick.eu>
License: MIT License
Project-URL: Documentation, https://django-snakeoil.readthedocs.io/en/latest/
Project-URL: Homepage, https://github.com/knyghty/django-snakeoil
Project-URL: Repository, https://github.com/knyghty/django-snakeoil
Keywords: django,seo,meta
Classifier: Development Status :: 5 - Production/Stable
Classifier: Environment :: Web Environment
Classifier: Framework :: Django
Classifier: Framework :: Django :: 4.2
Classifier: Framework :: Django :: 5.0
Classifier: Framework :: Django :: 5.1
Classifier: Intended Audience :: Developers
Classifier: License :: OSI Approved :: MIT License
Classifier: Operating System :: OS Independent
Classifier: Programming Language :: Python :: 3 :: Only
Classifier: Programming Language :: Python :: 3.9
Classifier: Programming Language :: Python :: 3.10
Classifier: Programming Language :: Python :: 3.11
Classifier: Programming Language :: Python :: 3.12
Classifier: Programming Language :: Python :: 3.13
Classifier: Topic :: Internet :: WWW/HTTP :: Site Management
Requires-Python: >=3.9
License-File: LICENSE
Requires-Dist: django
